cpupower.cp37-win_amd64.pyd
cpupower-1.0.1.dist-info/METADATA
cpupower-1.0.1.dist-info/WHEEL
cpupower-1.0.1.dist-info/top_level.txt
cpupower-1.0.1.dist-info/RECORD
