Metadata-Version: 2.1
Name: cpupower
Version: 1.0.1
Summary: Bindings for CPUpower proof of work used by CPUchain
Home-page: https://github.com/cpuchain/cpupower_python
Author: Min Khang Aung
Author-email: minkcrypto@gmail.com
License: UNKNOWN
Platform: UNKNOWN
